LICENSE
MANIFEST.in
history.md
readme.md
setup.py
examples/demo.fasta.gz
examples/demo.fastq.gz
examples/demo.m8
examples/demo.sam
humann/__init__.py
humann/check.py
humann/config.py
humann/humann.cfg
humann/humann.py
humann/store.py
humann/utilities.py
humann.egg-info/PKG-INFO
humann.egg-info/SOURCES.txt
humann.egg-info/dependency_links.txt
humann.egg-info/entry_points.txt
humann.egg-info/not-zip-safe
humann.egg-info/top_level.txt
humann/data/chocophlan_DEMO/g__Bacteroides.s__Bacteroides_dorei.centroids.v201901_v31.ffn.gz
humann/data/chocophlan_DEMO/g__Bacteroides.s__Bacteroides_vulgatus.centroids.v201901_v31.ffn.gz
humann/data/misc/KeggOrgId2OrgNameTable.txt
humann/data/misc/README.txt
humann/data/misc/humann3_sgb_map.Jun23.tsv
humann/data/misc/map_go_name.txt.gz
humann/data/misc/map_kegg-mdl_name.txt.gz
humann/data/misc/map_kegg-pwy_name.txt.gz
humann/data/misc/map_ko_name.txt.gz
humann/data/misc/map_level4ec_name.txt.gz
humann/data/misc/map_metacyc-pwy_name.txt.gz
humann/data/misc/map_metacyc-rxn_name.txt.gz
humann/data/misc/map_pfam_name.txt.gz
humann/data/misc/map_transporter_uniref50.txt.gz
humann/data/misc/map_uniref50_name.txt.bz2
humann/data/misc/mpa_vJan21_CHOCOPhlAnSGB_202103.tsv
humann/data/misc/vOct22_SGB_mapping.tsv
humann/data/pathways/metacyc_pathways
humann/data/pathways/metacyc_pathways_structured
humann/data/pathways/metacyc_pathways_structured_filtered
humann/data/pathways/metacyc_pathways_structured_filtered_v24
humann/data/pathways/metacyc_pathways_structured_filtered_v24_subreactions
humann/data/pathways/metacyc_pathways_structured_v24
humann/data/pathways/metacyc_pathways_to_organisms
humann/data/pathways/metacyc_reactions_level4ec_only.uniref.bz2
humann/data/pathways/unipathway_pathways
humann/data/pathways/unipathway_uniprots.uniref.bz2
humann/data/uniref_DEMO/uniref90_demo_prots_v201901b.dmnd
humann/data/uniref_DEMO/uniref90_demo_prots_v201901b.fna
humann/quantify/MinPath12hmp.py
humann/quantify/__init__.py
humann/quantify/chi2cdf.py
humann/quantify/families.py
humann/quantify/modules.py
humann/quantify/xipe.py
humann/search/__init__.py
humann/search/blastx_coverage.py
humann/search/nucleotide.py
