Metadata-Version: 1.1
Name: humann
Version: 3.9
Summary: HUMAnN: The HMP Unified Metabolic Analysis Network, version 3
Home-page: http://huttenhower.sph.harvard.edu/humann
Author: HUMAnN Development Team
Author-email: humann-users@googlegroups.com
License: MIT
Keywords: microbial,microbiome,bioinformatics,microbiology,metagenomic,metatranscriptomic,humann,humann
Platform: Linux
Platform: MacOS
Classifier: Programming Language :: Python
Classifier: Development Status :: 5 - Production/Stable
Classifier: Environment :: Console
Classifier: Operating System :: MacOS
Classifier: Operating System :: Unix
Classifier: Programming Language :: Python :: 2.7
Classifier: Programming Language :: Python :: 3.4
Classifier: Topic :: Scientific/Engineering :: Bio-Informatics
